[
    {
      "characterStats": {
        "statsMap": {
          "MAX_HEALTH": 100.0,
          "ARMOR": 0.0,
          "SPEED": 1.0,
          "MOVE_SPEED": 1.0,
          "RECOVERY": 1.0,
          "MIGHT": 1.0,
          "AREA": 1.0,
          "DURATION": 1.0,
          "AMOUNT": 1.0,
          "COOLDOWN": 1.0,
          "GROWTH": 1.0,
          "GREED": 1.0,
          "CURSE": 0.0,
          "MAGNET": 1.0,
          "REVIVAL": 0.0,
          "REROLL": 0.0,
          "SKIP": 0.0,
          "BANISH": 0.0
        }
      },
      "id": "characters/antonio",
      "name": "Antonio Belpaese",
      "description": "Il personaggio Antonio",
      "price": 100,
      "currentLevel": 0,
      "maxLevel": 0
    },
    {
      "characterStats": {
        "statsMap": {
          "MAX_HEALTH": 100.0,
          "ARMOR": 0.0,
          "SPEED": 1.0,
          "MOVE_SPEED": 1.0,
          "RECOVERY": 1.0,
          "MIGHT": 1.0,
          "AREA": 1.0,
          "DURATION": 1.0,
          "AMOUNT": 1.0,
          "COOLDOWN": 1.0,
          "GROWTH": 1.0,
          "GREED": 1.0,
          "CURSE": 0.0,
          "MAGNET": 1.0,
          "REVIVAL": 0.0,
          "REROLL": 0.0,
          "SKIP": 0.0,
          "BANISH": 0.0
        }
      },
      "id": "characters/imelda",
      "name": "Imelda Belpaese",
      "description": "Il personaggio Imelda",
      "price": 120,
      "currentLevel": 0,
      "maxLevel": 0
    },
    {
      "characterStats": {
        "statsMap": {
          "MAX_HEALTH": 100.0,
          "ARMOR": 0.0,
          "SPEED": 1.0,
          "MOVE_SPEED": 1.0,
          "RECOVERY": 1.0,
          "MIGHT": 1.0,
          "AREA": 1.0,
          "DURATION": 1.0,
          "AMOUNT": 1.0,
          "COOLDOWN": 1.0,
          "GROWTH": 1.0,
          "GREED": 1.0,
          "CURSE": 0.0,
          "MAGNET": 1.0,
          "REVIVAL": 0.0,
          "REROLL": 0.0,
          "SKIP": 0.0,
          "BANISH": 0.0
        }
      },
      "id": "characters/dommario",
      "name": "Dommario",
      "description": "Il personaggio Dommario",
      "price": 120,
      "currentLevel": 0,
      "maxLevel": 0
    },
    {
      "characterStats": {
        "statsMap": {
          "MAX_HEALTH": 100.0,
          "ARMOR": 0.0,
          "SPEED": 1.0,
          "MOVE_SPEED": 1.0,
          "RECOVERY": 1.0,
          "MIGHT": 1.0,
          "AREA": 1.0,
          "DURATION": 1.0,
          "AMOUNT": 1.0,
          "COOLDOWN": 1.0,
          "GROWTH": 1.0,
          "GREED": 1.0,
          "CURSE": 0.0,
          "MAGNET": 1.0,
          "REVIVAL": 0.0,
          "REROLL": 0.0,
          "SKIP": 0.0,
          "BANISH": 0.0
        }
      },
      "id": "characters/gennaro",
      "name": "Gennaro Belpaese",
      "description": "Il personaggio Gennaro",
      "price": 120,
      "currentLevel": 0,
      "maxLevel": 0
    }
  ]